nations_glory/__init__.py
nations_glory/countries.py
nations_glory/helpers.py
nations_glory/html.py
nations_glory/players.py
nations_glory-1.0.0.dist-info/LICENSE
nations_glory-1.0.0.dist-info/METADATA
nations_glory-1.0.0.dist-info/WHEEL
nations_glory-1.0.0.dist-info/top_level.txt
nations_glory-1.0.0.dist-info/RECORD
