Metadata-Version: 2.1
Name: nations-glory
Version: 1.0.0
Summary: A python library that collects information from nationsglory.fr, just for you.
Home-page: UNKNOWN
Author: galitan-dev
License: MIT
Platform: UNKNOWN
License-File: LICENSE
Requires-Dist: requests (==2.22.0)
Requires-Dist: html-to-json
